Metadata-Version: 1.0
Name: wireless
Version: 0.3.2
Summary: A dead simple, cross-platform Python library to connect to wireless networks.
Home-page: https://github.com/joshvillbrandt/wireless
Author: Josh Villbrandt
Author-email: josh@javconcepts.com
License: Apache License
